{"nodes": [{"id": "jquery_3_3_1_min", "label": "jquery.3.3.1.min.js", "file_type": "code", "source_file": "static/vendor/jquery.3.3.1.min.js", "source_location": "L1"}, {"id": "jquery_3_3_1_min_m", "label": "m()", "file_type": "code", "source_file": "static/vendor/jquery.3.3.1.min.js", "source_location": "L2"}, {"id": "jquery_3_3_1_min_x", "label": "x()", "file_type": "code", "source_file": "static/vendor/jquery.3.3.1.min.js", "source_location": "L2"}, {"id": "jquery_3_3_1_min_c", "label": "C()", "file_type": "code", "source_file": "static/vendor/jquery.3.3.1.min.js", "source_location": "L2"}, {"id": "jquery_3_3_1_min_oe", "label": "oe()", "file_type": "code", "source_file": "static/vendor/jquery.3.3.1.min.js", "source_location": "L2"}, {"id": "jquery_3_3_1_min_ae", "label": "ae()", "file_type": "code", "source_file": "static/vendor/jquery.3.3.1.min.js", "source_location": "L2"}, {"id": "jquery_3_3_1_min_se", "label": "se()", "file_type": "code", "source_file": "static/vendor/jquery.3.3.1.min.js", "source_location": "L2"}, {"id": "jquery_3_3_1_min_ue", "label": "ue()", "file_type": "code", "source_file": "static/vendor/jquery.3.3.1.min.js", "source_location": "L2"}, {"id": "jquery_3_3_1_min_le", "label": "le()", "file_type": "code", "source_file": "static/vendor/jquery.3.3.1.min.js", "source_location": "L2"}, {"id": "jquery_3_3_1_min_ce", "label": "ce()", "file_type": "code", "source_file": "static/vendor/jquery.3.3.1.min.js", "source_location": "L2"}, {"id": "jquery_3_3_1_min_fe", "label": "fe()", "file_type": "code", "source_file": "static/vendor/jquery.3.3.1.min.js", "source_location": "L2"}, {"id": "jquery_3_3_1_min_pe", "label": "pe()", "file_type": "code", "source_file": "static/vendor/jquery.3.3.1.min.js", "source_location": "L2"}, {"id": "jquery_3_3_1_min_de", "label": "de()", "file_type": "code", "source_file": "static/vendor/jquery.3.3.1.min.js", "source_location": "L2"}, {"id": "jquery_3_3_1_min_he", "label": "he()", "file_type": "code", "source_file": "static/vendor/jquery.3.3.1.min.js", "source_location": "L2"}, {"id": "jquery_3_3_1_min_ge", "label": "ge()", "file_type": "code", "source_file": "static/vendor/jquery.3.3.1.min.js", "source_location": "L2"}, {"id": "jquery_3_3_1_min_ye", "label": "ye()", "file_type": "code", "source_file": "static/vendor/jquery.3.3.1.min.js", "source_location": "L2"}, {"id": "jquery_3_3_1_min_ve", "label": "ve()", "file_type": "code", "source_file": "static/vendor/jquery.3.3.1.min.js", "source_location": "L2"}, {"id": "jquery_3_3_1_min_me", "label": "me()", "file_type": "code", "source_file": "static/vendor/jquery.3.3.1.min.js", "source_location": "L2"}, {"id": "jquery_3_3_1_min_xe", "label": "xe()", "file_type": "code", "source_file": "static/vendor/jquery.3.3.1.min.js", "source_location": "L2"}, {"id": "jquery_3_3_1_min_be", "label": "be()", "file_type": "code", "source_file": "static/vendor/jquery.3.3.1.min.js", "source_location": "L2"}, {"id": "jquery_3_3_1_min_we", "label": "we()", "file_type": "code", "source_file": "static/vendor/jquery.3.3.1.min.js", "source_location": "L2"}, {"id": "jquery_3_3_1_min_te", "label": "Te()", "file_type": "code", "source_file": "static/vendor/jquery.3.3.1.min.js", "source_location": "L2"}, {"id": "jquery_3_3_1_min_ee", "label": "Ee()", "file_type": "code", "source_file": "static/vendor/jquery.3.3.1.min.js", "source_location": "L2"}, {"id": "jquery_3_3_1_min_n", "label": "N()", "file_type": "code", "source_file": "static/vendor/jquery.3.3.1.min.js", "source_location": "L2"}, {"id": "jquery_3_3_1_min_j", "label": "j()", "file_type": "code", "source_file": "static/vendor/jquery.3.3.1.min.js", "source_location": "L2"}, {"id": "jquery_3_3_1_min_p", "label": "P()", "file_type": "code", "source_file": "static/vendor/jquery.3.3.1.min.js", "source_location": "L2"}, {"id": "jquery_3_3_1_min_r", "label": "R()", "file_type": "code", "source_file": "static/vendor/jquery.3.3.1.min.js", "source_location": "L2"}, {"id": "jquery_3_3_1_min_i", "label": "I()", "file_type": "code", "source_file": "static/vendor/jquery.3.3.1.min.js", "source_location": "L2"}, {"id": "jquery_3_3_1_min_w", "label": "W()", "file_type": "code", "source_file": "static/vendor/jquery.3.3.1.min.js", "source_location": "L2"}, {"id": "jquery_3_3_1_min_a", "label": "a()", "file_type": "code", "source_file": "static/vendor/jquery.3.3.1.min.js", "source_location": "L2"}, {"id": "jquery_3_3_1_min_v", "label": "V()", "file_type": "code", "source_file": "static/vendor/jquery.3.3.1.min.js", "source_location": "L2"}, {"id": "jquery_3_3_1_min_g", "label": "G()", "file_type": "code", "source_file": "static/vendor/jquery.3.3.1.min.js", "source_location": "L2"}, {"id": "jquery_3_3_1_min_q", "label": "Q()", "file_type": "code", "source_file": "static/vendor/jquery.3.3.1.min.js", "source_location": "L2"}, {"id": "jquery_3_3_1_min_ne", "label": "ne()", "file_type": "code", "source_file": "static/vendor/jquery.3.3.1.min.js", "source_location": "L2"}, {"id": "jquery_3_3_1_min_ke", "label": "ke()", "file_type": "code", "source_file": "static/vendor/jquery.3.3.1.min.js", "source_location": "L2"}, {"id": "jquery_3_3_1_min_re", "label": "Re()", "file_type": "code", "source_file": "static/vendor/jquery.3.3.1.min.js", "source_location": "L2"}, {"id": "jquery_3_3_1_min_ie", "label": "Ie()", "file_type": "code", "source_file": "static/vendor/jquery.3.3.1.min.js", "source_location": "L2"}, {"id": "jquery_3_3_1_min_t", "label": "t()", "file_type": "code", "source_file": "static/vendor/jquery.3.3.1.min.js", "source_location": "L2"}, {"id": "jquery_3_3_1_min_e", "label": "_e()", "file_type": "code", "source_file": "static/vendor/jquery.3.3.1.min.js", "source_location": "L2"}, {"id": "jquery_3_3_1_min_qe", "label": "Qe()", "file_type": "code", "source_file": "static/vendor/jquery.3.3.1.min.js", "source_location": "L2"}, {"id": "jquery_3_3_1_min_je", "label": "Je()", "file_type": "code", "source_file": "static/vendor/jquery.3.3.1.min.js", "source_location": "L2"}, {"id": "jquery_3_3_1_min_ze", "label": "Ze()", "file_type": "code", "source_file": "static/vendor/jquery.3.3.1.min.js", "source_location": "L2"}, {"id": "jquery_3_3_1_min_et", "label": "et()", "file_type": "code", "source_file": "static/vendor/jquery.3.3.1.min.js", "source_location": "L2"}, {"id": "jquery_3_3_1_min_tt", "label": "tt()", "file_type": "code", "source_file": "static/vendor/jquery.3.3.1.min.js", "source_location": "L2"}, {"id": "jquery_3_3_1_min_at", "label": "at()", "file_type": "code", "source_file": "static/vendor/jquery.3.3.1.min.js", "source_location": "L2"}, {"id": "jquery_3_3_1_min_st", "label": "st()", "file_type": "code", "source_file": "static/vendor/jquery.3.3.1.min.js", "source_location": "L2"}, {"id": "jquery_3_3_1_min_ut", "label": "ut()", "file_type": "code", "source_file": "static/vendor/jquery.3.3.1.min.js", "source_location": "L2"}, {"id": "jquery_3_3_1_min_lt", "label": "lt()", "file_type": "code", "source_file": "static/vendor/jquery.3.3.1.min.js", "source_location": "L2"}, {"id": "jquery_3_3_1_min_ct", "label": "ct()", "file_type": "code", "source_file": "static/vendor/jquery.3.3.1.min.js", "source_location": "L2"}, {"id": "jquery_3_3_1_min_ft", "label": "ft()", "file_type": "code", "source_file": "static/vendor/jquery.3.3.1.min.js", "source_location": "L2"}, {"id": "jquery_3_3_1_min_pt", "label": "pt()", "file_type": "code", "source_file": "static/vendor/jquery.3.3.1.min.js", "source_location": "L2"}, {"id": "jquery_3_3_1_min_vt", "label": "vt()", "file_type": "code", "source_file": "static/vendor/jquery.3.3.1.min.js", "source_location": "L2"}, {"id": "jquery_3_3_1_min_mt", "label": "mt()", "file_type": "code", "source_file": "static/vendor/jquery.3.3.1.min.js", "source_location": "L2"}, {"id": "jquery_3_3_1_min_xt", "label": "xt()", "file_type": "code", "source_file": "static/vendor/jquery.3.3.1.min.js", "source_location": "L2"}, {"id": "jquery_3_3_1_min_jt", "label": "jt()", "file_type": "code", "source_file": "static/vendor/jquery.3.3.1.min.js", "source_location": "L2"}, {"id": "jquery_3_3_1_min_zt", "label": "zt()", "file_type": "code", "source_file": "static/vendor/jquery.3.3.1.min.js", "source_location": "L2"}, {"id": "jquery_3_3_1_min_k", "label": "k()", "file_type": "code", "source_file": "static/vendor/jquery.3.3.1.min.js", "source_location": "L2"}], "edges": [{"source": "jquery_3_3_1_min", "target": "jquery_3_3_1_min_m", "relation": "contains", "confidence": "EXTRACTED", "source_file": "static/vendor/jquery.3.3.1.min.js", "source_location": "L2", "weight": 1.0}, {"source": "jquery_3_3_1_min", "target": "jquery_3_3_1_min_x", "relation": "contains", "confidence": "EXTRACTED", "source_file": "static/vendor/jquery.3.3.1.min.js", "source_location": "L2", "weight": 1.0}, {"source": "jquery_3_3_1_min", "target": "jquery_3_3_1_min_c", "relation": "contains", "confidence": "EXTRACTED", "source_file": "static/vendor/jquery.3.3.1.min.js", "source_location": "L2", "weight": 1.0}, {"source": "jquery_3_3_1_min", "target": "jquery_3_3_1_min_oe", "relation": "contains", "confidence": "EXTRACTED", "source_file": "static/vendor/jquery.3.3.1.min.js", "source_location": "L2", "weight": 1.0}, {"source": "jquery_3_3_1_min", "target": "jquery_3_3_1_min_ae", "relation": "contains", "confidence": "EXTRACTED", "source_file": "static/vendor/jquery.3.3.1.min.js", "source_location": "L2", "weight": 1.0}, {"source": "jquery_3_3_1_min", "target": "jquery_3_3_1_min_se", "relation": "contains", "confidence": "EXTRACTED", "source_file": "static/vendor/jquery.3.3.1.min.js", "source_location": "L2", "weight": 1.0}, {"source": "jquery_3_3_1_min", "target": "jquery_3_3_1_min_ue", "relation": "contains", "confidence": "EXTRACTED", "source_file": "static/vendor/jquery.3.3.1.min.js", "source_location": "L2", "weight": 1.0}, {"source": "jquery_3_3_1_min", "target": "jquery_3_3_1_min_le", "relation": "contains", "confidence": "EXTRACTED", "source_file": "static/vendor/jquery.3.3.1.min.js", "source_location": "L2", "weight": 1.0}, {"source": "jquery_3_3_1_min", "target": "jquery_3_3_1_min_ce", "relation": "contains", "confidence": "EXTRACTED", "source_file": "static/vendor/jquery.3.3.1.min.js", "source_location": "L2", "weight": 1.0}, {"source": "jquery_3_3_1_min", "target": "jquery_3_3_1_min_fe", "relation": "contains", "confidence": "EXTRACTED", "source_file": "static/vendor/jquery.3.3.1.min.js", "source_location": "L2", "weight": 1.0}, {"source": "jquery_3_3_1_min", "target": "jquery_3_3_1_min_pe", "relation": "contains", "confidence": "EXTRACTED", "source_file": "static/vendor/jquery.3.3.1.min.js", "source_location": "L2", "weight": 1.0}, {"source": "jquery_3_3_1_min", "target": "jquery_3_3_1_min_de", "relation": "contains", "confidence": "EXTRACTED", "source_file": "static/vendor/jquery.3.3.1.min.js", "source_location": "L2", "weight": 1.0}, {"source": "jquery_3_3_1_min", "target": "jquery_3_3_1_min_he", "relation": "contains", "confidence": "EXTRACTED", "source_file": "static/vendor/jquery.3.3.1.min.js", "source_location": "L2", "weight": 1.0}, {"source": "jquery_3_3_1_min", "target": "jquery_3_3_1_min_ge", "relation": "contains", "confidence": "EXTRACTED", "source_file": "static/vendor/jquery.3.3.1.min.js", "source_location": "L2", "weight": 1.0}, {"source": "jquery_3_3_1_min", "target": "jquery_3_3_1_min_ye", "relation": "contains", "confidence": "EXTRACTED", "source_file": "static/vendor/jquery.3.3.1.min.js", "source_location": "L2", "weight": 1.0}, {"source": "jquery_3_3_1_min", "target": "jquery_3_3_1_min_ve", "relation": "contains", "confidence": "EXTRACTED", "source_file": "static/vendor/jquery.3.3.1.min.js", "source_location": "L2", "weight": 1.0}, {"source": "jquery_3_3_1_min", "target": "jquery_3_3_1_min_me", "relation": "contains", "confidence": "EXTRACTED", "source_file": "static/vendor/jquery.3.3.1.min.js", "source_location": "L2", "weight": 1.0}, {"source": "jquery_3_3_1_min", "target": "jquery_3_3_1_min_xe", "relation": "contains", "confidence": "EXTRACTED", "source_file": "static/vendor/jquery.3.3.1.min.js", "source_location": "L2", "weight": 1.0}, {"source": "jquery_3_3_1_min", "target": "jquery_3_3_1_min_be", "relation": "contains", "confidence": "EXTRACTED", "source_file": "static/vendor/jquery.3.3.1.min.js", "source_location": "L2", "weight": 1.0}, {"source": "jquery_3_3_1_min", "target": "jquery_3_3_1_min_we", "relation": "contains", "confidence": "EXTRACTED", "source_file": "static/vendor/jquery.3.3.1.min.js", "source_location": "L2", "weight": 1.0}, {"source": "jquery_3_3_1_min", "target": "jquery_3_3_1_min_te", "relation": "contains", "confidence": "EXTRACTED", "source_file": "static/vendor/jquery.3.3.1.min.js", "source_location": "L2", "weight": 1.0}, {"source": "jquery_3_3_1_min", "target": "jquery_3_3_1_min_ce", "relation": "contains", "confidence": "EXTRACTED", "source_file": "static/vendor/jquery.3.3.1.min.js", "source_location": "L2", "weight": 1.0}, {"source": "jquery_3_3_1_min", "target": "jquery_3_3_1_min_ee", "relation": "contains", "confidence": "EXTRACTED", "source_file": "static/vendor/jquery.3.3.1.min.js", "source_location": "L2", "weight": 1.0}, {"source": "jquery_3_3_1_min", "target": "jquery_3_3_1_min_n", "relation": "contains", "confidence": "EXTRACTED", "source_file": "static/vendor/jquery.3.3.1.min.js", "source_location": "L2", "weight": 1.0}, {"source": "jquery_3_3_1_min", "target": "jquery_3_3_1_min_j", "relation": "contains", "confidence": "EXTRACTED", "source_file": "static/vendor/jquery.3.3.1.min.js", "source_location": "L2", "weight": 1.0}, {"source": "jquery_3_3_1_min", "target": "jquery_3_3_1_min_p", "relation": "contains", "confidence": "EXTRACTED", "source_file": "static/vendor/jquery.3.3.1.min.js", "source_location": "L2", "weight": 1.0}, {"source": "jquery_3_3_1_min", "target": "jquery_3_3_1_min_r", "relation": "contains", "confidence": "EXTRACTED", "source_file": "static/vendor/jquery.3.3.1.min.js", "source_location": "L2", "weight": 1.0}, {"source": "jquery_3_3_1_min", "target": "jquery_3_3_1_min_i", "relation": "contains", "confidence": "EXTRACTED", "source_file": "static/vendor/jquery.3.3.1.min.js", "source_location": "L2", "weight": 1.0}, {"source": "jquery_3_3_1_min", "target": "jquery_3_3_1_min_w", "relation": "contains", "confidence": "EXTRACTED", "source_file": "static/vendor/jquery.3.3.1.min.js", "source_location": "L2", "weight": 1.0}, {"source": "jquery_3_3_1_min", "target": "jquery_3_3_1_min", "relation": "contains", "confidence": "EXTRACTED", "source_file": "static/vendor/jquery.3.3.1.min.js", "source_location": "L2", "weight": 1.0}, {"source": "jquery_3_3_1_min", "target": "jquery_3_3_1_min_a", "relation": "contains", "confidence": "EXTRACTED", "source_file": "static/vendor/jquery.3.3.1.min.js", "source_location": "L2", "weight": 1.0}, {"source": "jquery_3_3_1_min", "target": "jquery_3_3_1_min", "relation": "contains", "confidence": "EXTRACTED", "source_file": "static/vendor/jquery.3.3.1.min.js", "source_location": "L2", "weight": 1.0}, {"source": "jquery_3_3_1_min", "target": "jquery_3_3_1_min_v", "relation": "contains", "confidence": "EXTRACTED", "source_file": "static/vendor/jquery.3.3.1.min.js", "source_location": "L2", "weight": 1.0}, {"source": "jquery_3_3_1_min", "target": "jquery_3_3_1_min_g", "relation": "contains", "confidence": "EXTRACTED", "source_file": "static/vendor/jquery.3.3.1.min.js", "source_location": "L2", "weight": 1.0}, {"source": "jquery_3_3_1_min", "target": "jquery_3_3_1_min_q", "relation": "contains", "confidence": "EXTRACTED", "source_file": "static/vendor/jquery.3.3.1.min.js", "source_location": "L2", "weight": 1.0}, {"source": "jquery_3_3_1_min", "target": "jquery_3_3_1_min_te", "relation": "contains", "confidence": "EXTRACTED", "source_file": "static/vendor/jquery.3.3.1.min.js", "source_location": "L2", "weight": 1.0}, {"source": "jquery_3_3_1_min", "target": "jquery_3_3_1_min_ne", "relation": "contains", "confidence": "EXTRACTED", "source_file": "static/vendor/jquery.3.3.1.min.js", "source_location": "L2", "weight": 1.0}, {"source": "jquery_3_3_1_min", "target": "jquery_3_3_1_min_ue", "relation": "contains", "confidence": "EXTRACTED", "source_file": "static/vendor/jquery.3.3.1.min.js", "source_location": "L2", "weight": 1.0}, {"source": "jquery_3_3_1_min", "target": "jquery_3_3_1_min_ce", "relation": "contains", "confidence": "EXTRACTED", "source_file": "static/vendor/jquery.3.3.1.min.js", "source_location": "L2", "weight": 1.0}, {"source": "jquery_3_3_1_min", "target": "jquery_3_3_1_min_fe", "relation": "contains", "confidence": "EXTRACTED", "source_file": "static/vendor/jquery.3.3.1.min.js", "source_location": "L2", "weight": 1.0}, {"source": "jquery_3_3_1_min", "target": "jquery_3_3_1_min_ye", "relation": "contains", "confidence": "EXTRACTED", "source_file": "static/vendor/jquery.3.3.1.min.js", "source_location": "L2", "weight": 1.0}, {"source": "jquery_3_3_1_min", "target": "jquery_3_3_1_min_ve", "relation": "contains", "confidence": "EXTRACTED", "source_file": "static/vendor/jquery.3.3.1.min.js", "source_location": "L2", "weight": 1.0}, {"source": "jquery_3_3_1_min", "target": "jquery_3_3_1_min_xe", "relation": "contains", "confidence": "EXTRACTED", "source_file": "static/vendor/jquery.3.3.1.min.js", "source_location": "L2", "weight": 1.0}, {"source": "jquery_3_3_1_min", "target": "jquery_3_3_1_min_ee", "relation": "contains", "confidence": "EXTRACTED", "source_file": "static/vendor/jquery.3.3.1.min.js", "source_location": "L2", "weight": 1.0}, {"source": "jquery_3_3_1_min", "target": "jquery_3_3_1_min_ke", "relation": "contains", "confidence": "EXTRACTED", "source_file": "static/vendor/jquery.3.3.1.min.js", "source_location": "L2", "weight": 1.0}, {"source": "jquery_3_3_1_min", "target": "jquery_3_3_1_min_se", "relation": "contains", "confidence": "EXTRACTED", "source_file": "static/vendor/jquery.3.3.1.min.js", "source_location": "L2", "weight": 1.0}, {"source": "jquery_3_3_1_min", "target": "jquery_3_3_1_min_de", "relation": "contains", "confidence": "EXTRACTED", "source_file": "static/vendor/jquery.3.3.1.min.js", "source_location": "L2", "weight": 1.0}, {"source": "jquery_3_3_1_min", "target": "jquery_3_3_1_min_le", "relation": "contains", "confidence": "EXTRACTED", "source_file": "static/vendor/jquery.3.3.1.min.js", "source_location": "L2", "weight": 1.0}, {"source": "jquery_3_3_1_min", "target": "jquery_3_3_1_min_he", "relation": "contains", "confidence": "EXTRACTED", "source_file": "static/vendor/jquery.3.3.1.min.js", "source_location": "L2", "weight": 1.0}, {"source": "jquery_3_3_1_min", "target": "jquery_3_3_1_min_oe", "relation": "contains", "confidence": "EXTRACTED", "source_file": "static/vendor/jquery.3.3.1.min.js", "source_location": "L2", "weight": 1.0}, {"source": "jquery_3_3_1_min", "target": "jquery_3_3_1_min_pe", "relation": "contains", "confidence": "EXTRACTED", "source_file": "static/vendor/jquery.3.3.1.min.js", "source_location": "L2", "weight": 1.0}, {"source": "jquery_3_3_1_min", "target": "jquery_3_3_1_min_me", "relation": "contains", "confidence": "EXTRACTED", "source_file": "static/vendor/jquery.3.3.1.min.js", "source_location": "L2", "weight": 1.0}, {"source": "jquery_3_3_1_min", "target": "jquery_3_3_1_min_re", "relation": "contains", "confidence": "EXTRACTED", "source_file": "static/vendor/jquery.3.3.1.min.js", "source_location": "L2", "weight": 1.0}, {"source": "jquery_3_3_1_min", "target": "jquery_3_3_1_min_ie", "relation": "contains", "confidence": "EXTRACTED", "source_file": "static/vendor/jquery.3.3.1.min.js", "source_location": "L2", "weight": 1.0}, {"source": "jquery_3_3_1_min", "target": "jquery_3_3_1_min_t", "relation": "contains", "confidence": "EXTRACTED", "source_file": "static/vendor/jquery.3.3.1.min.js", "source_location": "L2", "weight": 1.0}, {"source": "jquery_3_3_1_min", "target": "jquery_3_3_1_min_n", "relation": "contains", "confidence": "EXTRACTED", "source_file": "static/vendor/jquery.3.3.1.min.js", "source_location": "L2", "weight": 1.0}, {"source": "jquery_3_3_1_min", "target": "jquery_3_3_1_min_fe", "relation": "contains", "confidence": "EXTRACTED", "source_file": "static/vendor/jquery.3.3.1.min.js", "source_location": "L2", "weight": 1.0}, {"source": "jquery_3_3_1_min", "target": "jquery_3_3_1_min_e", "relation": "contains", "confidence": "EXTRACTED", "source_file": "static/vendor/jquery.3.3.1.min.js", "source_location": "L2", "weight": 1.0}, {"source": "jquery_3_3_1_min", "target": "jquery_3_3_1_min_qe", "relation": "contains", "confidence": "EXTRACTED", "source_file": "static/vendor/jquery.3.3.1.min.js", "source_location": "L2", "weight": 1.0}, {"source": "jquery_3_3_1_min", "target": "jquery_3_3_1_min_je", "relation": "contains", "confidence": "EXTRACTED", "source_file": "static/vendor/jquery.3.3.1.min.js", "source_location": "L2", "weight": 1.0}, {"source": "jquery_3_3_1_min", "target": "jquery_3_3_1_min_ke", "relation": "contains", "confidence": "EXTRACTED", "source_file": "static/vendor/jquery.3.3.1.min.js", "source_location": "L2", "weight": 1.0}, {"source": "jquery_3_3_1_min", "target": "jquery_3_3_1_min_ze", "relation": "contains", "confidence": "EXTRACTED", "source_file": "static/vendor/jquery.3.3.1.min.js", "source_location": "L2", "weight": 1.0}, {"source": "jquery_3_3_1_min", "target": "jquery_3_3_1_min_et", "relation": "contains", "confidence": "EXTRACTED", "source_file": "static/vendor/jquery.3.3.1.min.js", "source_location": "L2", "weight": 1.0}, {"source": "jquery_3_3_1_min", "target": "jquery_3_3_1_min_tt", "relation": "contains", "confidence": "EXTRACTED", "source_file": "static/vendor/jquery.3.3.1.min.js", "source_location": "L2", "weight": 1.0}, {"source": "jquery_3_3_1_min", "target": "jquery_3_3_1_min_at", "relation": "contains", "confidence": "EXTRACTED", "source_file": "static/vendor/jquery.3.3.1.min.js", "source_location": "L2", "weight": 1.0}, {"source": "jquery_3_3_1_min", "target": "jquery_3_3_1_min_st", "relation": "contains", "confidence": "EXTRACTED", "source_file": "static/vendor/jquery.3.3.1.min.js", "source_location": "L2", "weight": 1.0}, {"source": "jquery_3_3_1_min", "target": "jquery_3_3_1_min_ut", "relation": "contains", "confidence": "EXTRACTED", "source_file": "static/vendor/jquery.3.3.1.min.js", "source_location": "L2", "weight": 1.0}, {"source": "jquery_3_3_1_min", "target": "jquery_3_3_1_min_lt", "relation": "contains", "confidence": "EXTRACTED", "source_file": "static/vendor/jquery.3.3.1.min.js", "source_location": "L2", "weight": 1.0}, {"source": "jquery_3_3_1_min", "target": "jquery_3_3_1_min_ct", "relation": "contains", "confidence": "EXTRACTED", "source_file": "static/vendor/jquery.3.3.1.min.js", "source_location": "L2", "weight": 1.0}, {"source": "jquery_3_3_1_min", "target": "jquery_3_3_1_min_ft", "relation": "contains", "confidence": "EXTRACTED", "source_file": "static/vendor/jquery.3.3.1.min.js", "source_location": "L2", "weight": 1.0}, {"source": "jquery_3_3_1_min", "target": "jquery_3_3_1_min_pt", "relation": "contains", "confidence": "EXTRACTED", "source_file": "static/vendor/jquery.3.3.1.min.js", "source_location": "L2", "weight": 1.0}, {"source": "jquery_3_3_1_min", "target": "jquery_3_3_1_min_vt", "relation": "contains", "confidence": "EXTRACTED", "source_file": "static/vendor/jquery.3.3.1.min.js", "source_location": "L2", "weight": 1.0}, {"source": "jquery_3_3_1_min", "target": "jquery_3_3_1_min_mt", "relation": "contains", "confidence": "EXTRACTED", "source_file": "static/vendor/jquery.3.3.1.min.js", "source_location": "L2", "weight": 1.0}, {"source": "jquery_3_3_1_min", "target": "jquery_3_3_1_min_xt", "relation": "contains", "confidence": "EXTRACTED", "source_file": "static/vendor/jquery.3.3.1.min.js", "source_location": "L2", "weight": 1.0}, {"source": "jquery_3_3_1_min", "target": "jquery_3_3_1_min_jt", "relation": "contains", "confidence": "EXTRACTED", "source_file": "static/vendor/jquery.3.3.1.min.js", "source_location": "L2", "weight": 1.0}, {"source": "jquery_3_3_1_min", "target": "jquery_3_3_1_min_ft", "relation": "contains", "confidence": "EXTRACTED", "source_file": "static/vendor/jquery.3.3.1.min.js", "source_location": "L2", "weight": 1.0}, {"source": "jquery_3_3_1_min", "target": "jquery_3_3_1_min_t", "relation": "contains", "confidence": "EXTRACTED", "source_file": "static/vendor/jquery.3.3.1.min.js", "source_location": "L2", "weight": 1.0}, {"source": "jquery_3_3_1_min", "target": "jquery_3_3_1_min_zt", "relation": "contains", "confidence": "EXTRACTED", "source_file": "static/vendor/jquery.3.3.1.min.js", "source_location": "L2", "weight": 1.0}, {"source": "jquery_3_3_1_min", "target": "jquery_3_3_1_min_xt", "relation": "contains", "confidence": "EXTRACTED", "source_file": "static/vendor/jquery.3.3.1.min.js", "source_location": "L2", "weight": 1.0}, {"source": "jquery_3_3_1_min", "target": "jquery_3_3_1_min_ut", "relation": "contains", "confidence": "EXTRACTED", "source_file": "static/vendor/jquery.3.3.1.min.js", "source_location": "L2", "weight": 1.0}, {"source": "jquery_3_3_1_min", "target": "jquery_3_3_1_min_k", "relation": "contains", "confidence": "EXTRACTED", "source_file": "static/vendor/jquery.3.3.1.min.js", "source_location": "L2", "weight": 1.0}, {"source": "jquery_3_3_1_min_c", "target": "jquery_3_3_1_min_x", "relation": "calls", "confidence": "INFERRED", "source_file": "static/vendor/jquery.3.3.1.min.js", "source_location": "L2", "weight": 0.8}, {"source": "jquery_3_3_1_min_c", "target": "jquery_3_3_1_min_g", "relation": "calls", "confidence": "INFERRED", "source_file": "static/vendor/jquery.3.3.1.min.js", "source_location": "L2", "weight": 0.8}, {"source": "jquery_3_3_1_min_oe", "target": "jquery_3_3_1_min_p", "relation": "calls", "confidence": "INFERRED", "source_file": "static/vendor/jquery.3.3.1.min.js", "source_location": "L2", "weight": 0.8}, {"source": "jquery_3_3_1_min_oe", "target": "jquery_3_3_1_min_x", "relation": "calls", "confidence": "INFERRED", "source_file": "static/vendor/jquery.3.3.1.min.js", "source_location": "L2", "weight": 0.8}, {"source": "jquery_3_3_1_min_oe", "target": "jquery_3_3_1_min_a", "relation": "calls", "confidence": "INFERRED", "source_file": "static/vendor/jquery.3.3.1.min.js", "source_location": "L2", "weight": 0.8}, {"source": "jquery_3_3_1_min_oe", "target": "jquery_3_3_1_min_ve", "relation": "calls", "confidence": "INFERRED", "source_file": "static/vendor/jquery.3.3.1.min.js", "source_location": "L2", "weight": 0.8}, {"source": "jquery_3_3_1_min_oe", "target": "jquery_3_3_1_min_ge", "relation": "calls", "confidence": "INFERRED", "source_file": "static/vendor/jquery.3.3.1.min.js", "source_location": "L2", "weight": 0.8}, {"source": "jquery_3_3_1_min_de", "target": "jquery_3_3_1_min_ie", "relation": "calls", "confidence": "INFERRED", "source_file": "static/vendor/jquery.3.3.1.min.js", "source_location": "L2", "weight": 0.8}, {"source": "jquery_3_3_1_min_he", "target": "jquery_3_3_1_min_se", "relation": "calls", "confidence": "INFERRED", "source_file": "static/vendor/jquery.3.3.1.min.js", "source_location": "L2", "weight": 0.8}, {"source": "jquery_3_3_1_min_be", "target": "jquery_3_3_1_min_oe", "relation": "calls", "confidence": "INFERRED", "source_file": "static/vendor/jquery.3.3.1.min.js", "source_location": "L2", "weight": 0.8}, {"source": "jquery_3_3_1_min_we", "target": "jquery_3_3_1_min_n", "relation": "calls", "confidence": "INFERRED", "source_file": "static/vendor/jquery.3.3.1.min.js", "source_location": "L2", "weight": 0.8}, {"source": "jquery_3_3_1_min_te", "target": "jquery_3_3_1_min_se", "relation": "calls", "confidence": "INFERRED", "source_file": "static/vendor/jquery.3.3.1.min.js", "source_location": "L2", "weight": 0.8}, {"source": "jquery_3_3_1_min_te", "target": "jquery_3_3_1_min_be", "relation": "calls", "confidence": "INFERRED", "source_file": "static/vendor/jquery.3.3.1.min.js", "source_location": "L2", "weight": 0.8}, {"source": "jquery_3_3_1_min_te", "target": "jquery_3_3_1_min_we", "relation": "calls", "confidence": "INFERRED", "source_file": "static/vendor/jquery.3.3.1.min.js", "source_location": "L2", "weight": 0.8}, {"source": "jquery_3_3_1_min_te", "target": "jquery_3_3_1_min_n", "relation": "calls", "confidence": "INFERRED", "source_file": "static/vendor/jquery.3.3.1.min.js", "source_location": "L2", "weight": 0.8}, {"source": "jquery_3_3_1_min_te", "target": "jquery_3_3_1_min_r", "relation": "calls", "confidence": "INFERRED", "source_file": "static/vendor/jquery.3.3.1.min.js", "source_location": "L2", "weight": 0.8}, {"source": "jquery_3_3_1_min_te", "target": "jquery_3_3_1_min_i", "relation": "calls", "confidence": "INFERRED", "source_file": "static/vendor/jquery.3.3.1.min.js", "source_location": "L2", "weight": 0.8}, {"source": "jquery_3_3_1_min_ce", "target": "jquery_3_3_1_min_me", "relation": "calls", "confidence": "INFERRED", "source_file": "static/vendor/jquery.3.3.1.min.js", "source_location": "L2", "weight": 0.8}, {"source": "jquery_3_3_1_min_ce", "target": "jquery_3_3_1_min_c", "relation": "calls", "confidence": "INFERRED", "source_file": "static/vendor/jquery.3.3.1.min.js", "source_location": "L2", "weight": 0.8}, {"source": "jquery_3_3_1_min_ce", "target": "jquery_3_3_1_min_xe", "relation": "calls", "confidence": "INFERRED", "source_file": "static/vendor/jquery.3.3.1.min.js", "source_location": "L2", "weight": 0.8}, {"source": "jquery_3_3_1_min_ce", "target": "jquery_3_3_1_min_te", "relation": "calls", "confidence": "INFERRED", "source_file": "static/vendor/jquery.3.3.1.min.js", "source_location": "L2", "weight": 0.8}, {"source": "jquery_3_3_1_min_ce", "target": "jquery_3_3_1_min_ve", "relation": "calls", "confidence": "INFERRED", "source_file": "static/vendor/jquery.3.3.1.min.js", "source_location": "L2", "weight": 0.8}, {"source": "jquery_3_3_1_min_ee", "target": "jquery_3_3_1_min_p", "relation": "calls", "confidence": "INFERRED", "source_file": "static/vendor/jquery.3.3.1.min.js", "source_location": "L2", "weight": 0.8}, {"source": "jquery_3_3_1_min_ee", "target": "jquery_3_3_1_min_we", "relation": "calls", "confidence": "INFERRED", "source_file": "static/vendor/jquery.3.3.1.min.js", "source_location": "L2", "weight": 0.8}, {"source": "jquery_3_3_1_min_ee", "target": "jquery_3_3_1_min_se", "relation": "calls", "confidence": "INFERRED", "source_file": "static/vendor/jquery.3.3.1.min.js", "source_location": "L2", "weight": 0.8}, {"source": "jquery_3_3_1_min_j", "target": "jquery_3_3_1_min_g", "relation": "calls", "confidence": "INFERRED", "source_file": "static/vendor/jquery.3.3.1.min.js", "source_location": "L2", "weight": 0.8}, {"source": "jquery_3_3_1_min", "target": "jquery_3_3_1_min_g", "relation": "calls", "confidence": "INFERRED", "source_file": "static/vendor/jquery.3.3.1.min.js", "source_location": "L2", "weight": 0.8}, {"source": "jquery_3_3_1_min_a", "target": "jquery_3_3_1_min_g", "relation": "calls", "confidence": "INFERRED", "source_file": "static/vendor/jquery.3.3.1.min.js", "source_location": "L2", "weight": 0.8}, {"source": "jquery_3_3_1_min_a", "target": "jquery_3_3_1_min_c", "relation": "calls", "confidence": "INFERRED", "source_file": "static/vendor/jquery.3.3.1.min.js", "source_location": "L2", "weight": 0.8}, {"source": "jquery_3_3_1_min_ne", "target": "jquery_3_3_1_min_te", "relation": "calls", "confidence": "INFERRED", "source_file": "static/vendor/jquery.3.3.1.min.js", "source_location": "L2", "weight": 0.8}, {"source": "jquery_3_3_1_min_fe", "target": "jquery_3_3_1_min_ae", "relation": "calls", "confidence": "INFERRED", "source_file": "static/vendor/jquery.3.3.1.min.js", "source_location": "L2", "weight": 0.8}, {"source": "jquery_3_3_1_min_fe", "target": "jquery_3_3_1_min_ce", "relation": "calls", "confidence": "INFERRED", "source_file": "static/vendor/jquery.3.3.1.min.js", "source_location": "L2", "weight": 0.8}, {"source": "jquery_3_3_1_min_ye", "target": "jquery_3_3_1_min_n", "relation": "calls", "confidence": "INFERRED", "source_file": "static/vendor/jquery.3.3.1.min.js", "source_location": "L2", "weight": 0.8}, {"source": "jquery_3_3_1_min_xe", "target": "jquery_3_3_1_min_x", "relation": "calls", "confidence": "INFERRED", "source_file": "static/vendor/jquery.3.3.1.min.js", "source_location": "L2", "weight": 0.8}, {"source": "jquery_3_3_1_min_xe", "target": "jquery_3_3_1_min_ye", "relation": "calls", "confidence": "INFERRED", "source_file": "static/vendor/jquery.3.3.1.min.js", "source_location": "L2", "weight": 0.8}, {"source": "jquery_3_3_1_min_xe", "target": "jquery_3_3_1_min_ve", "relation": "calls", "confidence": "INFERRED", "source_file": "static/vendor/jquery.3.3.1.min.js", "source_location": "L2", "weight": 0.8}, {"source": "jquery_3_3_1_min_de", "target": "jquery_3_3_1_min_w", "relation": "calls", "confidence": "INFERRED", "source_file": "static/vendor/jquery.3.3.1.min.js", "source_location": "L2", "weight": 0.8}, {"source": "jquery_3_3_1_min_le", "target": "jquery_3_3_1_min_n", "relation": "calls", "confidence": "INFERRED", "source_file": "static/vendor/jquery.3.3.1.min.js", "source_location": "L2", "weight": 0.8}, {"source": "jquery_3_3_1_min_le", "target": "jquery_3_3_1_min_w", "relation": "calls", "confidence": "INFERRED", "source_file": "static/vendor/jquery.3.3.1.min.js", "source_location": "L2", "weight": 0.8}, {"source": "jquery_3_3_1_min_re", "target": "jquery_3_3_1_min_g", "relation": "calls", "confidence": "INFERRED", "source_file": "static/vendor/jquery.3.3.1.min.js", "source_location": "L2", "weight": 0.8}, {"source": "jquery_3_3_1_min_re", "target": "jquery_3_3_1_min_xe", "relation": "calls", "confidence": "INFERRED", "source_file": "static/vendor/jquery.3.3.1.min.js", "source_location": "L2", "weight": 0.8}, {"source": "jquery_3_3_1_min_re", "target": "jquery_3_3_1_min_ye", "relation": "calls", "confidence": "INFERRED", "source_file": "static/vendor/jquery.3.3.1.min.js", "source_location": "L2", "weight": 0.8}, {"source": "jquery_3_3_1_min_re", "target": "jquery_3_3_1_min_m", "relation": "calls", "confidence": "INFERRED", "source_file": "static/vendor/jquery.3.3.1.min.js", "source_location": "L2", "weight": 0.8}, {"source": "jquery_3_3_1_min_ie", "target": "jquery_3_3_1_min_ye", "relation": "calls", "confidence": "INFERRED", "source_file": "static/vendor/jquery.3.3.1.min.js", "source_location": "L2", "weight": 0.8}, {"source": "jquery_3_3_1_min_ie", "target": "jquery_3_3_1_min_ve", "relation": "calls", "confidence": "INFERRED", "source_file": "static/vendor/jquery.3.3.1.min.js", "source_location": "L2", "weight": 0.8}, {"source": "jquery_3_3_1_min_t", "target": "jquery_3_3_1_min_n", "relation": "calls", "confidence": "INFERRED", "source_file": "static/vendor/jquery.3.3.1.min.js", "source_location": "L2", "weight": 0.8}, {"source": "jquery_3_3_1_min_je", "target": "jquery_3_3_1_min_qe", "relation": "calls", "confidence": "INFERRED", "source_file": "static/vendor/jquery.3.3.1.min.js", "source_location": "L2", "weight": 0.8}, {"source": "jquery_3_3_1_min_et", "target": "jquery_3_3_1_min_fe", "relation": "calls", "confidence": "INFERRED", "source_file": "static/vendor/jquery.3.3.1.min.js", "source_location": "L2", "weight": 0.8}, {"source": "jquery_3_3_1_min_et", "target": "jquery_3_3_1_min_ze", "relation": "calls", "confidence": "INFERRED", "source_file": "static/vendor/jquery.3.3.1.min.js", "source_location": "L2", "weight": 0.8}, {"source": "jquery_3_3_1_min_ct", "target": "jquery_3_3_1_min_ae", "relation": "calls", "confidence": "INFERRED", "source_file": "static/vendor/jquery.3.3.1.min.js", "source_location": "L2", "weight": 0.8}, {"source": "jquery_3_3_1_min_ct", "target": "jquery_3_3_1_min_fe", "relation": "calls", "confidence": "INFERRED", "source_file": "static/vendor/jquery.3.3.1.min.js", "source_location": "L2", "weight": 0.8}, {"source": "jquery_3_3_1_min_ct", "target": "jquery_3_3_1_min_lt", "relation": "calls", "confidence": "INFERRED", "source_file": "static/vendor/jquery.3.3.1.min.js", "source_location": "L2", "weight": 0.8}, {"source": "jquery_3_3_1_min_ft", "target": "jquery_3_3_1_min_g", "relation": "calls", "confidence": "INFERRED", "source_file": "static/vendor/jquery.3.3.1.min.js", "source_location": "L2", "weight": 0.8}, {"source": "jquery_3_3_1_min_pt", "target": "jquery_3_3_1_min_st", "relation": "calls", "confidence": "INFERRED", "source_file": "static/vendor/jquery.3.3.1.min.js", "source_location": "L2", "weight": 0.8}, {"source": "jquery_3_3_1_min_pt", "target": "jquery_3_3_1_min_ft", "relation": "calls", "confidence": "INFERRED", "source_file": "static/vendor/jquery.3.3.1.min.js", "source_location": "L2", "weight": 0.8}, {"source": "jquery_3_3_1_min_pt", "target": "jquery_3_3_1_min_g", "relation": "calls", "confidence": "INFERRED", "source_file": "static/vendor/jquery.3.3.1.min.js", "source_location": "L2", "weight": 0.8}, {"source": "jquery_3_3_1_min_jt", "target": "jquery_3_3_1_min_r", "relation": "calls", "confidence": "INFERRED", "source_file": "static/vendor/jquery.3.3.1.min.js", "source_location": "L2", "weight": 0.8}, {"source": "jquery_3_3_1_min_jt", "target": "jquery_3_3_1_min_x", "relation": "calls", "confidence": "INFERRED", "source_file": "static/vendor/jquery.3.3.1.min.js", "source_location": "L2", "weight": 0.8}, {"source": "jquery_3_3_1_min_t", "target": "jquery_3_3_1_min_a", "relation": "calls", "confidence": "INFERRED", "source_file": "static/vendor/jquery.3.3.1.min.js", "source_location": "L2", "weight": 0.8}, {"source": "jquery_3_3_1_min_ut", "target": "jquery_3_3_1_min_a", "relation": "calls", "confidence": "INFERRED", "source_file": "static/vendor/jquery.3.3.1.min.js", "source_location": "L2", "weight": 0.8}, {"source": "jquery_3_3_1_min_k", "target": "jquery_3_3_1_min_xt", "relation": "calls", "confidence": "INFERRED", "source_file": "static/vendor/jquery.3.3.1.min.js", "source_location": "L2", "weight": 0.8}, {"source": "jquery_3_3_1_min_k", "target": "jquery_3_3_1_min_ut", "relation": "calls", "confidence": "INFERRED", "source_file": "static/vendor/jquery.3.3.1.min.js", "source_location": "L2", "weight": 0.8}]}